<?xml version="1.0" encoding="UTF-8"?>
<type name="SousthemeASE" superclass="com.jalios.jcms.Content" debatable="false" unitFieldEdition="true" audienced="false" categoryTab="true" readRightTab="true" updateRightTab="true" templateTab="true" workflowTab="true" advancedTab="true">
  <label xml:lang="fr">Sous-thème ASE</label>
  <title ml="true">
    <label xml:lang="en">Title</label>
    <label xml:lang="fr">Titre</label>
  </title>
  <fields>
    <field name="chapo" editor="textarea" required="false" compactDisplay="false" type="String" searchable="false" rows="5" cols="80" ml="true" wiki="false" html="false" wysiwygConfigurationId="" checkHtml="true">
      <label xml:lang="fr">Chapo</label>
    </field>
    <field name="contenu" editor="link" required="false" compactDisplay="false" type="com.jalios.jcms.Content[]">
      <label xml:lang="fr">Contenu</label>
    </field>
    <field name="estceQueCettePageTaAide" editor="boolean" required="false" compactDisplay="false" type="boolean" default="on">
      <label xml:lang="fr">Est-ce que cette page t'a aidé ?</label>
      <onLabel xml:lang="en">Yes</onLabel>
      <onLabel xml:lang="fr">Oui</onLabel>
      <offLabel xml:lang="en">No</offLabel>
      <offLabel xml:lang="fr">Non</offLabel>
    </field>
    <field name="navigation" editor="category" required="false" compactDisplay="false" type="java.util.TreeSet" chooser="tree" exclusive="true" root="$jcmsplugin.zelli.category.navigationParThemes.root">
      <label xml:lang="fr">Navigation</label>
    </field>
  </fields>
</type>

